{
    "products": [
        {
            "name": "Oculus Rift",
            "category": [],
            "price": 500,
            "image": 0
        },
        {
            "name": "Oculus Rift DK2",
            "category": [],
            "price": 200,
            "image": 0
        },
        {
            "name": "A screen",
            "category": [],
            "price": 200,
            "image": 0
        },
        {
            "name": "Another screen",
            "category": [],
            "price": 200,
            "image": 0
        },
        {
            "name": "fdsgsdg",
            "category": [],
            "price": "12",
            "image": "ghjghj"
        },
        {
            "name": "hgfhgfjhgjgh",
            "category": [],
            "price": "50",
            "image": "hfdfgh"
        },
        {
            "name": "dfgfdgdfg",
            "category": [
                "vr"
            ],
            "price": "50",
            "image": "hghgfhfgh"
        }
    ]
}